gleandoc/__init__.py
gleandoc/gleandoc.py
gleandoc-0.3.0.dist-info/entry_points.txt
gleandoc-0.3.0.dist-info/LICENSE
gleandoc-0.3.0.dist-info/WHEEL
gleandoc-0.3.0.dist-info/METADATA
gleandoc-0.3.0.dist-info/RECORD
