Metadata-Version: 2.1
Name: gleandoc
Version: 0.3.0
Summary: Convenience functions to extract docstring and write README
Home-page: https://github.com/datagazing/gleandoc
Author: Brendan Strejcek
Author-email: brendan@datagazing.com
Requires-Python: >=3.7
Classifier: License :: OSI Approved :: MIT License
